the_lord_of_the_rings_sdk/__init__.py
the_lord_of_the_rings_sdk/client.py
the_lord_of_the_rings_sdk/exceptions.py
the_lord_of_the_rings_sdk/models.py
the_lord_of_the_rings_sdk/utils.py
the_lord_of_the_rings_sdk/resources/__init__.py
the_lord_of_the_rings_sdk/resources/movie.py
the_lord_of_the_rings_sdk/tests/__init__.py
the_lord_of_the_rings_sdk/tests/test.py
the_lord_of_the_rings_sdk_danilredko-0.1.dist-info/METADATA
the_lord_of_the_rings_sdk_danilredko-0.1.dist-info/WHEEL
the_lord_of_the_rings_sdk_danilredko-0.1.dist-info/top_level.txt
the_lord_of_the_rings_sdk_danilredko-0.1.dist-info/RECORD
